romania_map/RomaniaMap.py
romania_map/__init__.py
Romania_Search-0.0.3.dist-info/METADATA
Romania_Search-0.0.3.dist-info/WHEEL
Romania_Search-0.0.3.dist-info/top_level.txt
Romania_Search-0.0.3.dist-info/RECORD
