Metadata-Version: 2.1
Name: Romania-Search
Version: 0.0.3
Summary: Multiple search algorithms in Romania map
Home-page: https://github.com/Raposones/Inteligencia-Artificial-2022.2
Author: Raphael Garcia
Author-email: raphaelgarcia0607@gmail.com
Requires-Python: >=3.8
